pydantic_identity/__init__.py
pydantic_identity/main.py
pydantic_identity/report.py
pydantic_identity/utils.py
pydantic_identity-0.0.2.dist-info/METADATA
pydantic_identity-0.0.2.dist-info/WHEEL
pydantic_identity-0.0.2.dist-info/licenses/LICENSE
pydantic_identity-0.0.2.dist-info/RECORD
